groupdocs_editor_cloud/__init__.py
groupdocs_editor_cloud/api_client.py
groupdocs_editor_cloud/api_exception.py
groupdocs_editor_cloud/auth.py
groupdocs_editor_cloud/configuration.py
groupdocs_editor_cloud/rest.py
groupdocs_editor_cloud/apis/__init__.py
groupdocs_editor_cloud/apis/edit_api.py
groupdocs_editor_cloud/apis/file_api.py
groupdocs_editor_cloud/apis/folder_api.py
groupdocs_editor_cloud/apis/info_api.py
groupdocs_editor_cloud/apis/license_api.py
groupdocs_editor_cloud/apis/storage_api.py
groupdocs_editor_cloud/models/__init__.py
groupdocs_editor_cloud/models/api_error.py
groupdocs_editor_cloud/models/api_error_response.py
groupdocs_editor_cloud/models/consumption_result.py
groupdocs_editor_cloud/models/delimited_text_load_options.py
groupdocs_editor_cloud/models/delimited_text_save_options.py
groupdocs_editor_cloud/models/disc_usage.py
groupdocs_editor_cloud/models/document_result.py
groupdocs_editor_cloud/models/error.py
groupdocs_editor_cloud/models/error_details.py
groupdocs_editor_cloud/models/file_info.py
groupdocs_editor_cloud/models/file_version.py
groupdocs_editor_cloud/models/file_versions.py
groupdocs_editor_cloud/models/files_list.py
groupdocs_editor_cloud/models/files_upload_result.py
groupdocs_editor_cloud/models/format.py
groupdocs_editor_cloud/models/formats_result.py
groupdocs_editor_cloud/models/info_result.py
groupdocs_editor_cloud/models/load_options.py
groupdocs_editor_cloud/models/load_result.py
groupdocs_editor_cloud/models/object_exist.py
groupdocs_editor_cloud/models/options.py
groupdocs_editor_cloud/models/pdf_save_options.py
groupdocs_editor_cloud/models/presentation_load_options.py
groupdocs_editor_cloud/models/presentation_save_options.py
groupdocs_editor_cloud/models/save_options.py
groupdocs_editor_cloud/models/spreadsheet_load_options.py
groupdocs_editor_cloud/models/spreadsheet_save_options.py
groupdocs_editor_cloud/models/storage_exist.py
groupdocs_editor_cloud/models/storage_file.py
groupdocs_editor_cloud-25.7.dist-info/licenses/LICENSE
groupdocs_editor_cloud-25.7.dist-info/METADATA
groupdocs_editor_cloud-25.7.dist-info/WHEEL
groupdocs_editor_cloud-25.7.dist-info/top_level.txt
groupdocs_editor_cloud-25.7.dist-info/RECORD
